jskos/__init__.py
jskos/__main__.py
jskos/api.py
jskos/cli.py
jskos/py.typed
jskos/version.py
jskos-0.0.5.dist-info/licenses/LICENSE
jskos-0.0.5.dist-info/WHEEL
jskos-0.0.5.dist-info/entry_points.txt
jskos-0.0.5.dist-info/METADATA
jskos-0.0.5.dist-info/RECORD
